easy_email_template/EmailTemplate.py
easy_email_template/__init__.py
easy_email_template-0.0.1.dist-info/licenses/LICENSE
easy_email_template-0.0.1.dist-info/METADATA
easy_email_template-0.0.1.dist-info/WHEEL
easy_email_template-0.0.1.dist-info/top_level.txt
easy_email_template-0.0.1.dist-info/RECORD
