Metadata-Version: 2.4
Name: easy_email_template
Version: 0.0.1
Summary: Email sending tempalte for beginers to send emails
Author: davidb@rumianocheese.com
Author-email: David Billingsley <daveandtaybillingsley@gmail.com>
Project-URL: Homepage, https://github.com/David-Billingsley/EmailTemplate
Project-URL: Issues, https://github.com/David-Billingsley/EmailTemplate/issues
Classifier: Programming Language :: Python :: 3
Classifier: License :: OSI Approved :: MIT License
Classifier: Operating System :: OS Independent
Requires-Python: >=3.8
License-File: LICENSE
Dynamic: author
Dynamic: license-file
